around_the_word/__init__.py
around_the_word/__main__.py
around_the_word/constants.py
around_the_word/map_generator.py
around_the_word/nationality.py
around_the_word/parsers.py
around_the_word/templates/map.html.j2
around_the_word-2.2.0.dist-info/WHEEL
around_the_word-2.2.0.dist-info/entry_points.txt
around_the_word-2.2.0.dist-info/METADATA
around_the_word-2.2.0.dist-info/RECORD
