Metadata-Version: 2.3
Name: around-the-word
Version: 2.2.0
Summary: Visualize a book list's author nationalities as a world heatmap
Author: nbr23
Author-email: nbr23 <max@23.tf>
License: MIT
Requires-Dist: requests
Requires-Dist: jinja2
Requires-Python: >=3.11
Project-URL: Homepage, https://www.github.com/nbr23/around-the-word
Project-URL: Repository, https://www.github.com/nbr23/around-the-word
Project-URL: Issues, https://github.com/nbr23/around-the-word/issues
